rljax/__init__.py
rljax/trainer.py
rljax/utils.py
rljax/algorithm/__init__.py
rljax/algorithm/base.py
rljax/algorithm/ddpg.py
rljax/algorithm/dqn.py
rljax/algorithm/fqf.py
rljax/algorithm/iqn.py
rljax/algorithm/ppo.py
rljax/algorithm/qrdqn.py
rljax/algorithm/sac.py
rljax/algorithm/sac_ae.py
rljax/algorithm/sac_discor.py
rljax/algorithm/sac_discrete.py
rljax/algorithm/slac.py
rljax/algorithm/td3.py
rljax/algorithm/tqc.py
rljax/algorithm/base_class/__init__.py
rljax/algorithm/base_class/actor_critic.py
rljax/algorithm/base_class/base_algoirithm.py
rljax/algorithm/base_class/q_learning.py
rljax/algorithm/misc/__init__.py
rljax/algorithm/misc/discor_mixin.py
rljax/algorithm/misc/slac_mixin.py
rljax/buffer/__init__.py
rljax/buffer/per.py
rljax/buffer/prioritized_buffer.py
rljax/buffer/replay_buffer.py
rljax/buffer/rollout_buffer.py
rljax/buffer/segment_tree.py
rljax/buffer/slac_buffer.py
rljax/common/__init__.py
rljax/common/base_class.py
rljax/common/policy.py
rljax/common/trainer.py
rljax/common/utils.py
rljax/common/value.py
rljax/common/buffer/__init__.py
rljax/common/buffer/per.py
rljax/common/buffer/replay_buffer.py
rljax/common/buffer/rollout_buffer.py
rljax/common/buffer/segment_tree.py
rljax/ddpg/__init__.py
rljax/ddpg/ddpg.py
rljax/ddpg/network.py
rljax/dqn/__init__.py
rljax/dqn/dqn.py
rljax/dqn/network.py
rljax/env/__init__.py
rljax/env/atari.py
rljax/env/continuous.py
rljax/env/mujoco/__init__.py
rljax/env/mujoco/dmc.py
rljax/network/__init__.py
rljax/network/actor.py
rljax/network/base.py
rljax/network/conv.py
rljax/network/critic.py
rljax/network/initializer.py
rljax/network/misc.py
rljax/ppo/__init__.py
rljax/ppo/network.py
rljax/ppo/ppo.py
rljax/sac/__init__.py
rljax/sac/network.py
rljax/sac/sac.py
rljax/sac_discrete/__init__.py
rljax/sac_discrete/network.py
rljax/sac_discrete/sac_discrete.py
rljax/td3/__init__.py
rljax/td3/network.py
rljax/td3/td3.py
rljax/trainer/__init__.py
rljax/trainer/base_trainer.py
rljax/trainer/slac_trainer.py
rljax-0.0.4.dist-info/LICENSE
rljax-0.0.4.dist-info/METADATA
rljax-0.0.4.dist-info/WHEEL
rljax-0.0.4.dist-info/top_level.txt
rljax-0.0.4.dist-info/RECORD
