Metadata-Version: 2.1
Name: rljax
Version: 0.0.4
Summary: A collection of RL algorithms written in JAX.
Home-page: https://github.com/ku2482/rljax
Author: Toshiki Watanabe
Author-email: watanabe.toshiki@outlook.jp
License: MIT
Platform: UNKNOWN
Classifier: License :: OSI Approved :: MIT License
Classifier: Programming Language :: Python
Classifier: Programming Language :: Python :: 3
Classifier: Programming Language :: Python :: 3.6
Classifier: Programming Language :: Python :: 3.7
Classifier: Programming Language :: Python :: 3.8
Classifier: Programming Language :: Python :: Implementation :: CPython
Classifier: Programming Language :: Python :: Implementation :: PyPy
Requires-Python: >=3.6.0
Requires-Dist: pyyaml (==5.3.1)
Requires-Dist: tqdm (==4.48.2)
Requires-Dist: numpy (==1.19.2)
Requires-Dist: pandas (==1.1.2)
Requires-Dist: dm-haiku (==0.0.2)
Requires-Dist: gym[atari] (==0.17.2)
Requires-Dist: dm-control (==0.0.322773188)
Requires-Dist: tensorboardX (==2.1)
